flutterwavedjango/__init__.py
flutterwavedjango/main.py
flutterwavedjango-1.1.11.dist-info/METADATA
flutterwavedjango-1.1.11.dist-info/WHEEL
flutterwavedjango-1.1.11.dist-info/RECORD
